spinelibs/__init__.py
spinelibs/pandas/__init__.py
spinelibs/pandas/steps/__init__.py
spinelibs/pandas/steps/io/__init__.py
spinelibs/pandas/steps/io/console/__init__.py
spinelibs/pandas/steps/io/console/console_writer.py
spinelibs/pandas/steps/io/csv/__init__.py
spinelibs/pandas/steps/io/csv/csv_reader.py
spinelibs/pandas/steps/io/csv/csv_writer.py
spinelibs/pandas/steps/io/sql/__init__.py
spinelibs/pandas/steps/io/sql/sql_reader.py
spinelibs/pandas/steps/io/sql/sql_writer.py
spinelibs/polars/__init__.py
spinelibs/polars/steps/__init__.py
spinelibs/polars/steps/general/GUIDColumn.py
spinelibs/polars/steps/general/__init__.py
spinelibs/polars/steps/io/__init__.py
spinelibs/polars/steps/io/console/__init__.py
spinelibs/polars/steps/io/console/console_writer.py
spinelibs/polars/steps/io/csv/__init__.py
spinelibs/polars/steps/io/csv/csv_reader.py
spinelibs/polars/steps/io/csv/csv_writer.py
spinelibs/polars/steps/io/sql/__init__.py
spinelibs/polars/steps/io/sql/sql_reader.py
spinelibs/polars/steps/io/sql/sql_writer.py
spinelibs/spark/__init__.py
spinelibs/spark/steps/__init__.py
spinelibs/spark/steps/io/__init__.py
spinelibs/spark/steps/io/console/__init__.py
spinelibs/spark/steps/io/console/console_writer.py
spinelibs/spark/steps/io/csv/__init__.py
spinelibs/spark/steps/io/csv/csv_reader.py
spinelibs/spark/steps/io/hdfs/__init__.py
spinelibs/spark/steps/io/hdfs/hdfs_reader.py
spinelibs/spark/steps/io/hdfs/hdfs_writer.py
spinelibs/spark/steps/io/hive/__init__.py
spinelibs/spark/steps/io/hive/hive_reader.py
spinelibs/spark/steps/io/hive/hive_writer.py
spinelibs/spark/steps/io/hive/sql_reader.py
spinelibs/spark/steps/io/jdbc/__init__.py
spinelibs/spark/steps/io/jdbc/jdbc_reader.py
spinelibs/spark/steps/io/jdbc/jdbc_writer.py
spinelibs/spark/steps/io/mssql/__init__.py
spinelibs/spark/steps/io/mssql/mssql_reader.py
spinelibs/spark/steps/io/mssql/mssql_writer.py
spinelibs-0.0.17.dist-info/METADATA
spinelibs-0.0.17.dist-info/WHEEL
spinelibs-0.0.17.dist-info/licenses/LICENSE
spinelibs-0.0.17.dist-info/RECORD
