Metadata-Version: 2.1
Name: spinelibs
Version: 0.0.17
Summary: Libs for spine project
Project-URL: Homepage, https://github.com/shaharluftig/spine
Author-email: Shahar Luftig <shaharluftig@gmail.com>
License:                                  Apache License
License-File: LICENSE
Keywords: core,dag,dataframe
Classifier: Intended Audience :: Science/Research
Classifier: Operating System :: OS Independent
Classifier: Programming Language :: Python
Classifier: Programming Language :: Python :: 3
Classifier: Programming Language :: Python :: 3 :: Only
Classifier: Programming Language :: Python :: 3.7
Classifier: Programming Language :: Python :: 3.8
Classifier: Programming Language :: Python :: 3.9
Classifier: Programming Language :: Python :: 3.10
Classifier: Programming Language :: Python :: 3.11
Classifier: Topic :: Scientific/Engineering
Requires-Python: >=3.7
Requires-Dist: spinecore
Provides-Extra: all
Requires-Dist: spinecore[pandas]; extra == 'all'
Requires-Dist: spinecore[polars]; extra == 'all'
Requires-Dist: spinecore[spark]; extra == 'all'
Provides-Extra: pandas
Requires-Dist: spinecore[pandas]; extra == 'pandas'
Provides-Extra: polars
Requires-Dist: spinecore[polars]; extra == 'polars'
Provides-Extra: spark
Requires-Dist: spinecore[spark]; extra == 'spark'
